rl_tasks/__init__.py
rl_tasks/task_executors/__init__.py
rl_tasks/task_executors/task_1_executor.py
rl_tasks/task_executors/task_2_executor.py
rl_tasks/task_executors/task_3_executor.py
rl_tasks/task_executors/task_chain.py
rl_tasks/task_executors/base/__init__.py
rl_tasks/task_executors/base/executor.py
rl_tasks/task_executors/base/task_executor.py
rl_tasks-0.1.7.dist-info/METADATA
rl_tasks-0.1.7.dist-info/WHEEL
rl_tasks-0.1.7.dist-info/top_level.txt
rl_tasks-0.1.7.dist-info/RECORD
